{
  "users": [
    {
      "name": "Alex Sachyan",
      "age": "25",
      "price": "12.000",
      "id": 1
    },
    {
      "name": "Arshak",
      "age": "25",
      "price": "78666",
      "id": 2
    },
    {
      "name": "Tamara",
      "age": "24",
      "price": "3.536",
      "id": 3
    },
    {
      "name": "Tamush",
      "age": "24",
      "price": "100.000",
      "id": 4
    },
    {
      "name": "mapasd1",
      "price": "v80",
      "age": "",
      "id": 8
    },
    {
      "name": "Ars",
      "price": "78666",
      "age": "29",
      "id": 9
    },
    {
      "name": "hj",
      "price": "190",
      "age": "25",
      "id": 10
    }
  ]
}